mahinmorsetext/__init__.py
mahinmorsetext/mahinmorsetext.py
mahinmorsetext-1.0.3.dist-info/LICENSE
mahinmorsetext-1.0.3.dist-info/METADATA
mahinmorsetext-1.0.3.dist-info/WHEEL
mahinmorsetext-1.0.3.dist-info/top_level.txt
mahinmorsetext-1.0.3.dist-info/RECORD
