Metadata-Version: 2.1
Name: mahinmorsetext
Version: 1.0.3
Summary: Morse to Text and text to morse Decoder and Encoder
Home-page: https://github.com/mahinbinhasan/morsetextencoder
Author: Mahin Bin Hasan (mahinbinhasan)
Author-email: <allmahin149@gmail.com>
Keywords: python,morsecode,morsetotext,decoder,encoder,morsedecoder
Classifier: Development Status :: 1 - Planning
Classifier: Programming Language :: Python :: 3
Classifier: Operating System :: Unix
Classifier: Operating System :: MacOS :: MacOS X
Classifier: Operating System :: Microsoft :: Windows
License-File: LICENSE
